mectrician/__init__.py
mectrician-0.0.0.dist-info/LICENSE
mectrician-0.0.0.dist-info/METADATA
mectrician-0.0.0.dist-info/WHEEL
mectrician-0.0.0.dist-info/top_level.txt
mectrician-0.0.0.dist-info/RECORD
