Metadata-Version: 2.1
Name: mectrician
Version: 0.0.0
Summary: Automatic metric logging for Pytorch
Home-page: https://github.com/tedtroxell/mectrician
Author: Ted Troxell
Author-email: ted@tedtroxell.com
License: UNKNOWN
Project-URL: Bug Tracker, https://github.com/tedtroxell/mectrician/issues
Platform: UNKNOWN
Classifier: Programming Language :: Python :: 3
Classifier: License :: OSI Approved :: MIT License
Classifier: Operating System :: OS Independent
Requires-Python: >=3.6
